wizard/__init__.py
wizard/atoms.py
wizard/calculator.py
wizard/frames.py
wizard/io.py
wizard/molecular_dynamics.py
wizard/phono.py
gpumd_wizard-0.0.2.dist-info/LICENSE
gpumd_wizard-0.0.2.dist-info/METADATA
gpumd_wizard-0.0.2.dist-info/WHEEL
gpumd_wizard-0.0.2.dist-info/top_level.txt
gpumd_wizard-0.0.2.dist-info/RECORD
