Metadata-Version: 2.1
Name: gpumd-wizard
Version: 0.0.2
Summary: Material structure processing software 
Home-page: https://github.com/Jonsnow-willow/GPUMD-Wizard
Author: Jiahui Liu
Author-email: jiahui.liu.willow@gmail.com
Classifier: Programming Language :: Python :: 3
Classifier: License :: OSI Approved :: MIT License
Classifier: Operating System :: OS Independent
Requires-Python: >=3.8
License-File: LICENSE
Requires-Dist: ase
Requires-Dist: phonopy
Requires-Dist: calorine
